setup.py
pytessert/__init__.py
pytessert/pytessert.py
pytessert.egg-info/PKG-INFO
pytessert.egg-info/SOURCES.txt
pytessert.egg-info/dependency_links.txt
pytessert.egg-info/requires.txt
pytessert.egg-info/top_level.txt