Metadata-Version: 1.0
Name: pytessert
Version: 0.0.1
Summary: Python-tesseract is a python wrapper for google's Tesseract-OCR
Home-page: UNKNOWN
Author: baituhuangyu
Author-email: baituhuangyu@qq.com
License: MIT License
Keywords: pytesser,pytesseract,pytessert
Platform: Ubuntu
